metathon/__init__.py
metathon/api.py
metathon/constants.py
metathon/device.py
metathon/useragent.py
metathon/utils.py
metathon-0.1.2.dist-info/METADATA
metathon-0.1.2.dist-info/WHEEL
metathon-0.1.2.dist-info/top_level.txt
metathon-0.1.2.dist-info/RECORD
