Metadata-Version: 2.1
Name: metathon
Version: 0.1.2
Summary: A Python wrapper for Meta social media API's
Home-page: https://pypi.org/project/metathon
Author: Moh Iqbal Hidayat
Author-email: iqbalmh18.dev@gmail.com
Classifier: Programming Language :: Python :: 3
Classifier: License :: OSI Approved :: MIT License
Classifier: Operating System :: OS Independent
Requires-Python: >=3.9
Requires-Dist: requests
Requires-Dist: pycryptodomex
